holmes/.git_archival.json
holmes/__init__.py
holmes/clients/robusta_client.py
holmes/common/env_vars.py
holmes/common/openshift.py
holmes/config.py
holmes/core/__init__.py
holmes/core/config.py
holmes/core/conversations.py
holmes/core/feedback.py
holmes/core/investigation.py
holmes/core/investigation_structured_output.py
holmes/core/issue.py
holmes/core/llm.py
holmes/core/models.py
holmes/core/openai_formatting.py
holmes/core/prompt.py
holmes/core/resource_instruction.py
holmes/core/runbooks.py
holmes/core/safeguards.py
holmes/core/supabase_dal.py
holmes/core/todo_tasks_formatter.py
holmes/core/tool_calling_llm.py
holmes/core/tools.py
holmes/core/tools_utils/__init__.py
holmes/core/tools_utils/token_counting.py
holmes/core/tools_utils/tool_context_window_limiter.py
holmes/core/tools_utils/tool_executor.py
holmes/core/tools_utils/toolset_utils.py
holmes/core/toolset_manager.py
holmes/core/tracing.py
holmes/core/transformers/__init__.py
holmes/core/transformers/base.py
holmes/core/transformers/llm_summarize.py
holmes/core/transformers/registry.py
holmes/core/transformers/transformer.py
holmes/core/truncation/compaction.py
holmes/core/truncation/dal_truncation_utils.py
holmes/core/truncation/input_context_window_limiter.py
holmes/interactive.py
holmes/main.py
holmes/plugins/__init__.py
holmes/plugins/destinations/__init__.py
holmes/plugins/destinations/slack/__init__.py
holmes/plugins/destinations/slack/plugin.py
holmes/plugins/interfaces.py
holmes/plugins/prompts/__init__.py
holmes/plugins/prompts/_ai_safety.jinja2
holmes/plugins/prompts/_current_date_time.jinja2
holmes/plugins/prompts/_default_log_prompt.jinja2
holmes/plugins/prompts/_fetch_logs.jinja2
holmes/plugins/prompts/_general_instructions.jinja2
holmes/plugins/prompts/_global_instructions.jinja2
holmes/plugins/prompts/_permission_errors.jinja2
holmes/plugins/prompts/_runbook_instructions.jinja2
holmes/plugins/prompts/_toolsets_instructions.jinja2
holmes/plugins/prompts/base_user_prompt.jinja2
holmesgpt-0.18.4.dist-info/LICENSE
holmesgpt-0.18.4.dist-info/METADATA
holmesgpt-0.18.4.dist-info/WHEEL
holmesgpt-0.18.4.dist-info/entry_points.txt
holmesgpt-0.18.4.dist-info/RECORD
