Metadata-Version: 2.1
Name: holmesgpt
Version: 0.18.4
Summary: 
Author: Natan Yellin
Author-email: natan@robusta.dev
Requires-Python: >=3.10,<4.0
Classifier: Programming Language :: Python :: 3
Classifier: Programming Language :: Python :: 3.10
Classifier: Programming Language :: Python :: 3.11
Requires-Dist: ag-ui-protocol (>=0.1.9,<0.2.0)
Requires-Dist: azure-core (>=1.34.0,<2.0.0)
Requires-Dist: azure-identity (>=1.23.0,<2.0.0)
Requires-Dist: azure-mgmt-alertsmanagement (>=1.0.0,<2.0.0)
Requires-Dist: azure-mgmt-monitor (>=7.0.0b1,<8.0.0)
Requires-Dist: azure-mgmt-resource (>=23.3.0,<24.0.0)
Requires-Dist: azure-mgmt-sql (>=4.0.0b21,<5.0.0)
Requires-Dist: azure-monitor-query (>=1.2.0,<2.0.0)
Requires-Dist: backoff (>=2.2.1,<3.0.0)
Requires-Dist: boto3 (>=1.34.145,<2.0.0)
Requires-Dist: bs4 (>=0.0.2,<0.0.3)
Requires-Dist: cachetools (>=5.5.0,<6.0.0)
Requires-Dist: certifi (>=2024.7.4,<2025.0.0)
Requires-Dist: colorlog (>=6.8.2,<7.0.0)
Requires-Dist: confluent-kafka (>=2.6.1,<3.0.0)
Requires-Dist: fastapi (>=0.116,<0.117)
Requires-Dist: google-cloud-aiplatform (>=1.38)
Requires-Dist: httpx[socks] (<0.28)
Requires-Dist: humanize (>=4.9.0,<5.0.0)
Requires-Dist: jinja2 (>=3.1.2,<4.0.0)
Requires-Dist: jq (>=1.10.0,<2.0.0)
Requires-Dist: kubernetes (>=32.0.1,<33.0.0)
Requires-Dist: litellm (==1.77.1)
Requires-Dist: markdown (>=3.6,<4.0)
Requires-Dist: markdownify (>=1.1.0,<2.0.0)
Requires-Dist: mcp (==v1.12.2)
Requires-Dist: openai (>=1.6.1,<1.100.0)
Requires-Dist: opensearch-py (>=2.8.0,<3.0.0)
Requires-Dist: postgrest (==0.16.8)
Requires-Dist: prometrix (==0.2.5)
Requires-Dist: prompt-toolkit (>=3.0.51,<4.0.0)
Requires-Dist: pydantic (>=2.7,<3.0)
Requires-Dist: pygments (>=2.18.0,<3.0.0)
Requires-Dist: pyodbc (>=5.0.1,<6.0.0)
Requires-Dist: python-benedict (>=0.33.1,<0.34.0)
Requires-Dist: requests (>=2.32.4,<3.0.0)
Requires-Dist: requests-aws4auth (>=1.3.1,<2.0.0)
Requires-Dist: rich (>=13.7.1,<14.0.0)
Requires-Dist: sentry-sdk[fastapi] (>=2.20.0,<3.0.0)
Requires-Dist: strenum (>=0.4.15,<0.5.0)
Requires-Dist: supabase (>=2.5,<3.0)
Requires-Dist: tenacity (>=9.1.2,<10.0.0)
Requires-Dist: typer (>=0.15.4,<0.16.0)
Requires-Dist: uvicorn (>=0.30,<0.31)
